ccsm_cc/__main__.py
ccsm_cc/argument_parser.py
ccsm_cc/options/__init__.py
ccsm_cc/options/common.py
ccsm_cc/options/first_run.py
ccsm_cc/options/menus.py
ccsm_cc/options/options.py
ccsm_cc/sav_ops/__init__.py
ccsm_cc/sav_ops/from_neocrab.py
ccsm_cc/sav_ops/loader.py
ccsm_cc/sav_ops/to_neocrab.py
ccsm_cc-0.0.1.dist-info/METADATA
ccsm_cc-0.0.1.dist-info/WHEEL
ccsm_cc-0.0.1.dist-info/top_level.txt
ccsm_cc-0.0.1.dist-info/RECORD
