Metadata-Version: 2.1
Name: ccsm-cc
Version: 0.0.1
Summary: A Simple and Easy-to-Use Save Manager for Crab Champions
Author-email: CJ <cjendantix@proton.me>
License: Unlicense
Classifier: Development Status :: 2 - Pre-Alpha
Classifier: Environment :: Console :: Curses
Classifier: License :: OSI Approved :: The Unlicense (Unlicense)
Classifier: Typing :: Typed
Classifier: Programming Language :: Python :: 3
Classifier: Operating System :: OS Independent
Requires-Python: >=3.12
Requires-Dist: ui-forge
Requires-Dist: SavConverter
Requires-Dist: pathvalidate
